[{"description":"ASOS 4505 unisex gilet with pocket detail","orginalPrice":2800,"newPrice":1680,"discount":40,"url":"https://www.asos.com/asos-4505/asos-4505-unisex-gilet-with-pocket-detail/prd/23418013?colourwayid=60480884&cid=3606","orderId":4,"imgUrl":"","changedBy":0},{"description":"ASOS 4505 unisex shacket in brushed back","orginalPrice":3200,"newPrice":1920,"discount":40,"url":"https://www.asos.com/asos-4505/asos-4505-unisex-shacket-in-brushed-back/prd/23418022?colourwayid=60480895&cid=3606","orderId":5,"imgUrl":"","changedBy":0}]